vkr_sync_hdl/files (4)/sync_mod1_nco.v
`timescale 1ns / 1ps
//==========================================================================
// Модуль       : sync_mod1_nco
// Описание     : Вычитающий счётчик по модулю 1 (Mod-1 NCO)
//                μ = CNT_old / W — полноценное деление.
//                Для синтеза заменяется на Divider IP или LUT(1/W).
//
// Автор        : Кудимов А.А., ВКР магистра, 2026
//==========================================================================
module sync_mod1_nco #(
    parameter W_CNT = 16,
    parameter W_MU  = 12,
    parameter W_W   = 16
)(
    input  wire                          clk,
    input  wire                          reset,
    input  wire                          in_valid,
    input  wire        [W_W-1:0]         w_step,
    output reg                           strobe,
    output reg         [W_MU-1:0]        mu_out
);

localparam W_EXT = W_CNT + 1;

reg [W_CNT-1:0] cnt_reg;

// Детекция underflow
wire [W_EXT-1:0] cnt_ext   = {1'b0, cnt_reg};
wire [W_EXT-1:0] w_ext     = {1'b0, w_step[W_W-1:W_W-W_CNT]};
wire [W_EXT-1:0] cnt_next  = cnt_ext - w_ext;
wire             underflow = cnt_next[W_EXT-1];

wire [W_CNT-1:0] cnt_wrap  = cnt_next[W_CNT-1:0];

// =========================================================================
// Полноценное деление μ = CNT_old / W
// μ_Q = (CNT_old << W_MU) / w_step
// Результат в Q0.W_MU, диапазон [0, 1)
//
// Для симуляции: поведенческое деление (synthesizable через Divider IP)
// =========================================================================
wire [W_CNT + W_MU - 1:0] cnt_shifted = {cnt_reg, {W_MU{1'b0}}};
wire [W_CNT + W_MU - 1:0] mu_full     = (w_step != 0) ? cnt_shifted / w_step : 0;
wire [W_MU-1:0]           mu_calc     = mu_full[W_MU-1:0];

// =========================================================================
// Основной автомат
// =========================================================================
always @(posedge clk or posedge reset) begin
    if (reset) begin
        cnt_reg <= {1'b1, {(W_CNT-1){1'b0}}};  // CNT_init = W_nom = 0.5
        strobe  <= 1'b0;
        mu_out  <= {W_MU{1'b0}};
    end else if (in_valid) begin
        if (underflow) begin
            cnt_reg <= cnt_wrap;
            strobe  <= 1'b1;
            mu_out  <= mu_calc;
        end else begin
            cnt_reg <= cnt_next[W_CNT-1:0];
            strobe  <= 1'b0;
        end
    end else begin
        strobe <= 1'b0;
    end
end

endmodule

vkr_sync_hdl/sim/tb_sync_mod1_nco.v
`timescale 1ns / 1ps
//==========================================================================
// Тестбенч     : tb_sync_mod1_nco
// Описание     : Верификация модуля sync_mod1_nco
//                Подаёт постоянный W = W_nom = 0.5 (0x8000 для W_W=16),
//                проверяет, что strobe срабатывает каждые 2 такта (sps_rx=2).
//                Затем меняет W и проверяет изменение частоты стробирования.
//==========================================================================
module tb_sync_mod1_nco;

localparam W_CNT = 16;
localparam W_MU  = 12;
localparam W_W   = 16;
localparam CLK_PERIOD = 16;   // нс

reg                  clk;
reg                  reset;
reg                  in_valid;
reg  [W_W-1:0]       w_step;
wire                 strobe;
wire [W_MU-1:0]      mu_out;

sync_mod1_nco #(
    .W_CNT (W_CNT),
    .W_MU  (W_MU),
    .W_W   (W_W)
) dut (
    .clk      (clk),
    .reset    (reset),
    .in_valid (in_valid),
    .w_step   (w_step),
    .strobe   (strobe),
    .mu_out   (mu_out)
);

initial clk = 1'b0;
always #(CLK_PERIOD/2) clk = ~clk;

integer fout;
integer n;
integer strobe_count;
integer total_clocks;

initial begin
    $dumpfile("tb_sync_mod1_nco.vcd");
    $dumpvars(0, tb_sync_mod1_nco);

    fout = $fopen("nco_out.txt", "w");

    reset    = 1'b1;
    in_valid = 1'b0;
    w_step   = 16'h8000;   // W_nom = 0.5 → sps_rx = 2

    @(posedge clk); @(posedge clk); @(posedge clk);
    @(negedge clk) reset = 1'b0;
    @(posedge clk);

    // ============ Тест 1: W = 0.5 (номинал), 100 тактов ============
    $display("[Test 1] W = 0.5 (0x8000), expect strobe every 2 clocks");
    strobe_count = 0;
    total_clocks = 100;
    for (n = 0; n < total_clocks; n = n + 1) begin
        @(negedge clk);
        in_valid = 1'b1;
        @(posedge clk);
        #1;
        $fwrite(fout, "%0d %0d %0d %0d\n", n, strobe, mu_out, w_step);
        if (strobe) strobe_count = strobe_count + 1;
    end
    @(negedge clk) in_valid = 1'b0;
    $display("[Test 1] Strobes: %0d in %0d clocks (expected ~%0d)",
             strobe_count, total_clocks, total_clocks/2);

    repeat(5) @(posedge clk);

    // ============ Тест 2: W = 0.4 (< номинала → sps > 2) ============
    $display("[Test 2] W = 0.4 (0x6666), expect strobe every ~2.5 clocks");
    w_step = 16'h6666;   // ≈ 0.4
    strobe_count = 0;
    total_clocks = 100;
    for (n = 0; n < total_clocks; n = n + 1) begin
        @(negedge clk);
        in_valid = 1'b1;
        @(posedge clk);
        #1;
        $fwrite(fout, "%0d %0d %0d %0d\n", n, strobe, mu_out, w_step);
        if (strobe) strobe_count = strobe_count + 1;
    end
    @(negedge clk) in_valid = 1'b0;
    $display("[Test 2] Strobes: %0d in %0d clocks (expected ~%0d)",
             strobe_count, total_clocks, 100*4/10);  // 100 * 0.4 = 40

    repeat(5) @(posedge clk);

    // ============ Тест 3: W = 0.6 (> номинала → sps < 2) ============
    $display("[Test 3] W = 0.6 (0x999A), expect strobe every ~1.67 clocks");
    w_step = 16'h999A;   // ≈ 0.6
    strobe_count = 0;
    total_clocks = 100;
    for (n = 0; n < total_clocks; n = n + 1) begin
        @(negedge clk);
        in_valid = 1'b1;
        @(posedge clk);
        #1;
        $fwrite(fout, "%0d %0d %0d %0d\n", n, strobe, mu_out, w_step);
        if (strobe) strobe_count = strobe_count + 1;
    end
    @(negedge clk) in_valid = 1'b0;
    $display("[Test 3] Strobes: %0d in %0d clocks (expected ~%0d)",
             strobe_count, total_clocks, 100*6/10);  // 100 * 0.6 = 60

    $fclose(fout);
    $display("[tb_sync_mod1_nco] Done");
    $finish;
end

endmodule

vkr_sync_hdl/vivado_prj_nco/sync_mod1_nco_test.sim/sim_1/behav/xsim/tb_sync_mod1_nco.vcd
$date
   Tue May 12 16:09:22 2026
$end

$version
  2023.2
  $dumpfile ("tb_sync_mod1_nco.vcd") 
$end

$timescale
  1ps
$end

$scope module tb_sync_mod1_nco $end
$var reg 1 ! clk $end
$var reg 1 " reset $end
$var reg 1 # in_valid $end
$var reg 16 $ w_step [15:0] $end
$var wire 1 % strobe $end
$var wire 12 & mu_out [11:0] $end
$var integer 32 ' fout [31:0] $end
$var integer 32 ( n [31:0] $end
$var integer 32 ) strobe_count [31:0] $end
$var integer 32 * total_clocks [31:0] $end
$scope module dut $end
$var wire 1 + clk $end
$var wire 1 , reset $end
$var wire 1 - in_valid $end
$var wire 16 . w_step [15:0] $end
$var reg 1 / strobe $end
$var reg 12 0 mu_out [11:0] $end
$var reg 16 1 cnt_reg [15:0] $end
$var wire 17 2 cnt_ext [16:0] $end
$var wire 17 3 w_ext [16:0] $end
$var wire 17 4 cnt_next [16:0] $end
$var wire 1 5 underflow $end
$var wire 16 6 cnt_wrap [15:0] $end
$var wire 28 7 cnt_shifted [27:0] $end
$var wire 28 8 mu_full [27:0] $end
$var wire 12 9 mu_calc [11:0] $end
$upscope $end
$upscope $end
$enddefinitions $end

#0
$dumpvars
0!
1"
0#
b1000000000000000 $
0%
b0 &
b11111111111111111011000111100000 '
bx (
bx )
bx *
0+
1,
0-
b1000000000000000 .
0/
b0 0
b1000000000000000 1
b1000000000000000 2
b1000000000000000 3
b0 4
05
b0 6
b1000000000000000000000000000 7
b1000000000000 8
b0 9
$end

#8000
1!
1+

#16000
0!
0+

#24000
1!
1+

#32000
0!
0+

#40000
1!
1+

#48000
0!
0"
0+
0,

#56000
1!
b0 (
b0 )
b1100100 *
1+

#64000
0!
1#
0+
1-

#72000
1!
1+
b0 1
b0 2
b11000000000000000 4
15
b1000000000000000 6
b0 7
b0 8

#73000
b1 (

#80000
0!
0+

#88000
1!
1%
1+
1/
b1000000000000000 1
b1000000000000000 2
b0 4
05
b0 6
b1000000000000000000000000000 7
b1000000000000 8

#89000
b10 (
b1 )

#96000
0!
0+

#104000
1!
0%
1+
0/
b0 1
b0 2
b11000000000000000 4
15
b1000000000000000 6
b0 7
b0 8

#105000
b11 (

#112000
0!
0+

#120000
1!
1%
1+
1/
b1000000000000000 1
b1000000000000000 2
b0 4
05
b0 6
b1000000000000000000000000000 7
b1000000000000 8

#121000
b100 (
b10 )

#128000
0!
0+

#136000
1!
0%
1+
0/
b0 1
b0 2
b11000000000000000 4
15
b1000000000000000 6
b0 7
b0 8

#137000
b101 (

#144000
0!
0+

#152000
1!
1%
1+
1/
b1000000000000000 1
b1000000000000000 2
b0 4
05
b0 6
b1000000000000000000000000000 7
b1000000000000 8

#153000
b110 (
b11 )

#160000
0!
0+

#168000
1!
0%
1+
0/
b0 1
b0 2
b11000000000000000 4
15
b1000000000000000 6
b0 7
b0 8

#169000
b111 (

#176000
0!
0+

#184000
1!
1%
1+
1/
b1000000000000000 1
b1000000000000000 2
b0 4
05
b0 6
b1000000000000000000000000000 7
b1000000000000 8

#185000
b1000 (
b100 )

#192000
0!
0+

#200000
1!
0%
1+
0/
b0 1
b0 2
b11000000000000000 4
15
b1000000000000000 6
b0 7
b0 8

#201000
b1001 (

#208000
0!
0+

#216000
1!
1%
1+
1/
b1000000000000000 1
b1000000000000000 2
b0 4
05
b0 6
b1000000000000000000000000000 7
b1000000000000 8

#217000
b1010 (
b101 )

#224000
0!
0+

#232000
1!
0%
1+
0/
b0 1
b0 2
b11000000000000000 4
15
b1000000000000000 6
b0 7
b0 8

#233000
b1011 (

#240000
0!
0+

#248000
1!
1%
1+
1/
b1000000000000000 1
b1000000000000000 2
b0 4
05
b0 6
b1000000000000000000000000000 7
b1000000000000 8

#249000
b1100 (
b110 )

#256000
0!
0+

#264000
1!
0%
1+
0/
b0 1
b0 2
b11000000000000000 4
15
b1000000000000000 6
b0 7
b0 8

#265000
b1101 (

#272000
0!
0+

#280000
1!
1%
1+
1/
b1000000000000000 1
b1000000000000000 2
b0 4
05
b0 6
b1000000000000000000000000000 7
b1000000000000 8

#281000
b1110 (
b111 )

#288000
0!
0+

#296000
1!
0%
1+
0/
b0 1
b0 2
b11000000000000000 4
15
b1000000000000000 6
b0 7
b0 8

#297000
b1111 (

#304000
0!
0+

#312000
1!
1%
1+
1/
b1000000000000000 1
b1000000000000000 2
b0 4
05
b0 6
b1000000000000000000000000000 7
b1000000000000 8

#313000
b10000 (
b1000 )

#320000
0!
0+

#328000
1!
0%
1+
0/
b0 1
b0 2
b11000000000000000 4
15
b1000000000000000 6
b0 7
b0 8

#329000
b10001 (

#336000
0!
0+

#344000
1!
1%
1+
1/
b1000000000000000 1
b1000000000000000 2
b0 4
05
b0 6
b1000000000000000000000000000 7
b1000000000000 8

#345000
b10010 (
b1001 )

#352000
0!
0+

#360000
1!
0%
1+
0/
b0 1
b0 2
b11000000000000000 4
15
b1000000000000000 6
b0 7
b0 8

#361000
b10011 (

#368000
0!
0+

#376000
1!
1%
1+
1/
b1000000000000000 1
b1000000000000000 2
b0 4
05
b0 6
b1000000000000000000000000000 7
b1000000000000 8

#377000
b10100 (
b1010 )

#384000
0!
0+

#392000
1!
0%
1+
0/
b0 1
b0 2
b11000000000000000 4
15
b1000000000000000 6
b0 7
b0 8

#393000
b10101 (

#400000
0!
0+

#408000
1!
1%
1+
1/
b1000000000000000 1
b1000000000000000 2
b0 4
05
b0 6
b1000000000000000000000000000 7
b1000000000000 8

#409000
b10110 (
b1011 )

#416000
0!
0+

#424000
1!
0%
1+
0/
b0 1
b0 2
b11000000000000000 4
15
b1000000000000000 6
b0 7
b0 8

#425000
b10111 (

#432000
0!
0+

#440000
1!
1%
1+
1/
b1000000000000000 1
b1000000000000000 2
b0 4
05
b0 6
b1000000000000000000000000000 7
b1000000000000 8

#441000
b11000 (
b1100 )

#448000
0!
0+

#456000
1!
0%
1+
0/
b0 1
b0 2
b11000000000000000 4
15
b1000000000000000 6
b0 7
b0 8

#457000
b11001 (

#464000
0!
0+

#472000
1!
1%
1+
1/
b1000000000000000 1
b1000000000000000 2
b0 4
05
b0 6
b1000000000000000000000000000 7
b1000000000000 8

#473000
b11010 (
b1101 )

#480000
0!
0+

#488000
1!
0%
1+
0/
b0 1
b0 2
b11000000000000000 4
15
b1000000000000000 6
b0 7
b0 8

#489000
b11011 (

#496000
0!
0+

#504000
1!
1%
1+
1/
b1000000000000000 1
b1000000000000000 2
b0 4
05
b0 6
b1000000000000000000000000000 7
b1000000000000 8

#505000
b11100 (
b1110 )

#512000
0!
0+

#520000
1!
0%
1+
0/
b0 1
b0 2
b11000000000000000 4
15
b1000000000000000 6
b0 7
b0 8

#521000
b11101 (

#528000
0!
0+

#536000
1!
1%
1+
1/
b1000000000000000 1
b1000000000000000 2
b0 4
05
b0 6
b1000000000000000000000000000 7
b1000000000000 8

#537000
b11110 (
b1111 )

#544000
0!
0+

#552000
1!
0%
1+
0/
b0 1
b0 2
b11000000000000000 4
15
b1000000000000000 6
b0 7
b0 8

#553000
b11111 (

#560000
0!
0+

#568000
1!
1%
1+
1/
b1000000000000000 1
b1000000000000000 2
b0 4
05
b0 6
b1000000000000000000000000000 7
b1000000000000 8

#569000
b100000 (
b10000 )

#576000
0!
0+

#584000
1!
0%
1+
0/
b0 1
b0 2
b11000000000000000 4
15
b1000000000000000 6
b0 7
b0 8

#585000
b100001 (

#592000
0!
0+

#600000
1!
1%
1+
1/
b1000000000000000 1
b1000000000000000 2
b0 4
05
b0 6
b1000000000000000000000000000 7
b1000000000000 8

#601000
b100010 (
b10001 )

#608000
0!
0+

#616000
1!
0%
1+
0/
b0 1
b0 2
b11000000000000000 4
15
b1000000000000000 6
b0 7
b0 8

#617000
b100011 (

#624000
0!
0+

#632000
1!
1%
1+
1/
b1000000000000000 1
b1000000000000000 2
b0 4
05
b0 6
b1000000000000000000000000000 7
b1000000000000 8

#633000
b100100 (
b10010 )

#640000
0!
0+

#648000
1!
0%
1+
0/
b0 1
b0 2
b11000000000000000 4
15
b1000000000000000 6
b0 7
b0 8

#649000
b100101 (

#656000
0!
0+

#664000
1!
1%
1+
1/
b1000000000000000 1
b1000000000000000 2
b0 4
05
b0 6
b1000000000000000000000000000 7
b1000000000000 8

#665000
b100110 (
b10011 )

#672000
0!
0+

#680000
1!
0%
1+
0/
b0 1
b0 2
b11000000000000000 4
15
b1000000000000000 6
b0 7
b0 8

#681000
b100111 (

#688000
0!
0+

#696000
1!
1%
1+
1/
b1000000000000000 1
b1000000000000000 2
b0 4
05
b0 6
b1000000000000000000000000000 7
b1000000000000 8

#697000
b101000 (
b10100 )

#704000
0!
0+

#712000
1!
0%
1+
0/
b0 1
b0 2
b11000000000000000 4
15
b1000000000000000 6
b0 7
b0 8

#713000
b101001 (

#720000
0!
0+

#728000
1!
1%
1+
1/
b1000000000000000 1
b1000000000000000 2
b0 4
05
b0 6
b1000000000000000000000000000 7
b1000000000000 8

#729000
b101010 (
b10101 )

#736000
0!
0+

#744000
1!
0%
1+
0/
b0 1
b0 2
b11000000000000000 4
15
b1000000000000000 6
b0 7
b0 8

#745000
b101011 (

#752000
0!
0+

#760000
1!
1%
1+
1/
b1000000000000000 1
b1000000000000000 2
b0 4
05
b0 6
b1000000000000000000000000000 7
b1000000000000 8

#761000
b101100 (
b10110 )

#768000
0!
0+

#776000
1!
0%
1+
0/
b0 1
b0 2
b11000000000000000 4
15
b1000000000000000 6
b0 7
b0 8

#777000
b101101 (

#784000
0!
0+

#792000
1!
1%
1+
1/
b1000000000000000 1
b1000000000000000 2
b0 4
05
b0 6
b1000000000000000000000000000 7
b1000000000000 8

#793000
b101110 (
b10111 )

#800000
0!
0+

#808000
1!
0%
1+
0/
b0 1
b0 2
b11000000000000000 4
15
b1000000000000000 6
b0 7
b0 8

#809000
b101111 (

#816000
0!
0+

#824000
1!
1%
1+
1/
b1000000000000000 1
b1000000000000000 2
b0 4
05
b0 6
b1000000000000000000000000000 7
b1000000000000 8

#825000
b110000 (
b11000 )

#832000
0!
0+

#840000
1!
0%
1+
0/
b0 1
b0 2
b11000000000000000 4
15
b1000000000000000 6
b0 7
b0 8

#841000
b110001 (

#848000
0!
0+

#856000
1!
1%
1+
1/
b1000000000000000 1
b1000000000000000 2
b0 4
05
b0 6
b1000000000000000000000000000 7
b1000000000000 8

#857000
b110010 (
b11001 )

#864000
0!
0+

#872000
1!
0%
1+
0/
b0 1
b0 2
b11000000000000000 4
15
b1000000000000000 6
b0 7
b0 8

#873000
b110011 (

#880000
0!
0+

#888000
1!
1%
1+
1/
b1000000000000000 1
b1000000000000000 2
b0 4
05
b0 6
b1000000000000000000000000000 7
b1000000000000 8

#889000
b110100 (
b11010 )

#896000
0!
0+

#904000
1!
0%
1+
0/
b0 1
b0 2
b11000000000000000 4
15
b1000000000000000 6
b0 7
b0 8

#905000
b110101 (

#912000
0!
0+

#920000
1!
1%
1+
1/
b1000000000000000 1
b1000000000000000 2
b0 4
05
b0 6
b1000000000000000000000000000 7
b1000000000000 8

#921000
b110110 (
b11011 )

#928000
0!
0+

#936000
1!
0%
1+
0/
b0 1
b0 2
b11000000000000000 4
15
b1000000000000000 6
b0 7
b0 8

#937000
b110111 (

#944000
0!
0+

#952000
1!
1%
1+
1/
b1000000000000000 1
b1000000000000000 2
b0 4
05
b0 6
b1000000000000000000000000000 7
b1000000000000 8

#953000
b111000 (
b11100 )

#960000
0!
0+

#968000
1!
0%
1+
0/
b0 1
b0 2
b11000000000000000 4
15
b1000000000000000 6
b0 7
b0 8

#969000
b111001 (

#976000
0!
0+

#984000
1!
1%
1+
1/
b1000000000000000 1
b1000000000000000 2
b0 4
05
b0 6
b1000000000000000000000000000 7
b1000000000000 8

#985000
b111010 (
b11101 )

#992000
0!
0+

#1000000
1!
0%
1+
0/
b0 1
b0 2
b11000000000000000 4
15
b1000000000000000 6
b0 7
b0 8

#1001000
b111011 (

#1008000
0!
0+

#1016000
1!
1%
1+
1/
b1000000000000000 1
b1000000000000000 2
b0 4
05
b0 6
b1000000000000000000000000000 7
b1000000000000 8

#1017000
b111100 (
b11110 )

#1024000
0!
0+

#1032000
1!
0%
1+
0/
b0 1
b0 2
b11000000000000000 4
15
b1000000000000000 6
b0 7
b0 8

#1033000
b111101 (

#1040000
0!
0+

#1048000
1!
1%
1+
1/
b1000000000000000 1
b1000000000000000 2
b0 4
05
b0 6
b1000000000000000000000000000 7
b1000000000000 8

#1049000
b111110 (
b11111 )

#1056000
0!
0+

#1064000
1!
0%
1+
0/
b0 1
b0 2
b11000000000000000 4
15
b1000000000000000 6
b0 7
b0 8

#1065000
b111111 (

#1072000
0!
0+

#1080000
1!
1%
1+
1/
b1000000000000000 1
b1000000000000000 2
b0 4
05
b0 6
b1000000000000000000000000000 7
b1000000000000 8

#1081000
b1000000 (
b100000 )

#1088000
0!
0+

#1096000
1!
0%
1+
0/
b0 1
b0 2
b11000000000000000 4
15
b1000000000000000 6
b0 7
b0 8

#1097000
b1000001 (

#1104000
0!
0+

#1112000
1!
1%
1+
1/
b1000000000000000 1
b1000000000000000 2
b0 4
05
b0 6
b1000000000000000000000000000 7
b1000000000000 8

#1113000
b1000010 (
b100001 )

#1120000
0!
0+

#1128000
1!
0%
1+
0/
b0 1
b0 2
b11000000000000000 4
15
b1000000000000000 6
b0 7
b0 8

#1129000
b1000011 (

#1136000
0!
0+

#1144000
1!
1%
1+
1/
b1000000000000000 1
b1000000000000000 2
b0 4
05
b0 6
b1000000000000000000000000000 7
b1000000000000 8

#1145000
b1000100 (
b100010 )

#1152000
0!
0+

#1160000
1!
0%
1+
0/
b0 1
b0 2
b11000000000000000 4
15
b1000000000000000 6
b0 7
b0 8

#1161000
b1000101 (

#1168000
0!
0+

#1176000
1!
1%
1+
1/
b1000000000000000 1
b1000000000000000 2
b0 4
05
b0 6
b1000000000000000000000000000 7
b1000000000000 8

#1177000
b1000110 (
b100011 )

#1184000
0!
0+

#1192000
1!
0%
1+
0/
b0 1
b0 2
b11000000000000000 4
15
b1000000000000000 6
b0 7
b0 8

#1193000
b1000111 (

#1200000
0!
0+

#1208000
1!
1%
1+
1/
b1000000000000000 1
b1000000000000000 2
b0 4
05
b0 6
b1000000000000000000000000000 7
b1000000000000 8

#1209000
b1001000 (
b100100 )

#1216000
0!
0+

#1224000
1!
0%
1+
0/
b0 1
b0 2
b11000000000000000 4
15
b1000000000000000 6
b0 7
b0 8

#1225000
b1001001 (

#1232000
0!
0+

#1240000
1!
1%
1+
1/
b1000000000000000 1
b1000000000000000 2
b0 4
05
b0 6
b1000000000000000000000000000 7
b1000000000000 8

#1241000
b1001010 (
b100101 )

#1248000
0!
0+

#1256000
1!
0%
1+
0/
b0 1
b0 2
b11000000000000000 4
15
b1000000000000000 6
b0 7
b0 8

#1257000
b1001011 (

#1264000
0!
0+

#1272000
1!
1%
1+
1/
b1000000000000000 1
b1000000000000000 2
b0 4
05
b0 6
b1000000000000000000000000000 7
b1000000000000 8

#1273000
b1001100 (
b100110 )

#1280000
0!
0+

#1288000
1!
0%
1+
0/
b0 1
b0 2
b11000000000000000 4
15
b1000000000000000 6
b0 7
b0 8

#1289000
b1001101 (

#1296000
0!
0+

#1304000
1!
1%
1+
1/
b1000000000000000 1
b1000000000000000 2
b0 4
05
b0 6
b1000000000000000000000000000 7
b1000000000000 8

#1305000
b1001110 (
b100111 )

#1312000
0!
0+

#1320000
1!
0%
1+
0/
b0 1
b0 2
b11000000000000000 4
15
b1000000000000000 6
b0 7
b0 8

#1321000
b1001111 (

#1328000
0!
0+

#1336000
1!
1%
1+
1/
b1000000000000000 1
b1000000000000000 2
b0 4
05
b0 6
b1000000000000000000000000000 7
b1000000000000 8

#1337000
b1010000 (
b101000 )

#1344000
0!
0+

#1352000
1!
0%
1+
0/
b0 1
b0 2
b11000000000000000 4
15
b1000000000000000 6
b0 7
b0 8

#1353000
b1010001 (

#1360000
0!
0+

#1368000
1!
1%
1+
1/
b1000000000000000 1
b1000000000000000 2
b0 4
05
b0 6
b1000000000000000000000000000 7
b1000000000000 8

#1369000
b1010010 (
b101001 )

#1376000
0!
0+

#1384000
1!
0%
1+
0/
b0 1
b0 2
b11000000000000000 4
15
b1000000000000000 6
b0 7
b0 8

#1385000
b1010011 (

#1392000
0!
0+

#1400000
1!
1%
1+
1/
b1000000000000000 1
b1000000000000000 2
b0 4
05
b0 6
b1000000000000000000000000000 7
b1000000000000 8

#1401000
b1010100 (
b101010 )

#1408000
0!
0+

#1416000
1!
0%
1+
0/
b0 1
b0 2
b11000000000000000 4
15
b1000000000000000 6
b0 7
b0 8

#1417000
b1010101 (

#1424000
0!
0+

#1432000
1!
1%
1+
1/
b1000000000000000 1
b1000000000000000 2
b0 4
05
b0 6
b1000000000000000000000000000 7
b1000000000000 8

#1433000
b1010110 (
b101011 )

#1440000
0!
0+

#1448000
1!
0%
1+
0/
b0 1
b0 2
b11000000000000000 4
15
b1000000000000000 6
b0 7
b0 8

#1449000
b1010111 (

#1456000
0!
0+

#1464000
1!
1%
1+
1/
b1000000000000000 1
b1000000000000000 2
b0 4
05
b0 6
b1000000000000000000000000000 7
b1000000000000 8

#1465000
b1011000 (
b101100 )

#1472000
0!
0+

#1480000
1!
0%
1+
0/
b0 1
b0 2
b11000000000000000 4
15
b1000000000000000 6
b0 7
b0 8

#1481000
b1011001 (

#1488000
0!
0+

#1496000
1!
1%
1+
1/
b1000000000000000 1
b1000000000000000 2
b0 4
05
b0 6
b1000000000000000000000000000 7
b1000000000000 8

#1497000
b1011010 (
b101101 )

#1504000
0!
0+

#1512000
1!
0%
1+
0/
b0 1
b0 2
b11000000000000000 4
15
b1000000000000000 6
b0 7
b0 8

#1513000
b1011011 (

#1520000
0!
0+

#1528000
1!
1%
1+
1/
b1000000000000000 1
b1000000000000000 2
b0 4
05
b0 6
b1000000000000000000000000000 7
b1000000000000 8

#1529000
b1011100 (
b101110 )

#1536000
0!
0+

#1544000
1!
0%
1+
0/
b0 1
b0 2
b11000000000000000 4
15
b1000000000000000 6
b0 7
b0 8

#1545000
b1011101 (

#1552000
0!
0+

#1560000
1!
1%
1+
1/
b1000000000000000 1
b1000000000000000 2
b0 4
05
b0 6
b1000000000000000000000000000 7
b1000000000000 8

#1561000
b1011110 (
b101111 )

#1568000
0!
0+

#1576000
1!
0%
1+
0/
b0 1
b0 2
b11000000000000000 4
15
b1000000000000000 6
b0 7
b0 8

#1577000
b1011111 (

#1584000
0!
0+

#1592000
1!
1%
1+
1/
b1000000000000000 1
b1000000000000000 2
b0 4
05
b0 6
b1000000000000000000000000000 7
b1000000000000 8

#1593000
b1100000 (
b110000 )

#1600000
0!
0+

#1608000
1!
0%
1+
0/
b0 1
b0 2
b11000000000000000 4
15
b1000000000000000 6
b0 7
b0 8

#1609000
b1100001 (

#1616000
0!
0+

#1624000
1!
1%
1+
1/
b1000000000000000 1
b1000000000000000 2
b0 4
05
b0 6
b1000000000000000000000000000 7
b1000000000000 8

#1625000
b1100010 (
b110001 )

#1632000
0!
0+

#1640000
1!
0%
1+
0/
b0 1
b0 2
b11000000000000000 4
15
b1000000000000000 6
b0 7
b0 8

#1641000
b1100011 (

#1648000
0!
0+

#1656000
1!
1%
1+
1/
b1000000000000000 1
b1000000000000000 2
b0 4
05
b0 6
b1000000000000000000000000000 7
b1000000000000 8

#1657000
b1100100 (
b110010 )

#1664000
0!
0#
0+
0-

#1672000
1!
0%
1+
0/

#1680000
0!
0+

#1688000
1!
1+

#1696000
0!
0+

#1704000
1!
1+

#1712000
0!
0+

#1720000
1!
1+

#1728000
0!
0+

#1736000
1!
b110011001100110 $
b0 (
b0 )
1+
b110011001100110 .
b110011001100110 3
b1100110011010 4
b1100110011010 6
b1010000000000 8
b10000000000 9

#1744000
0!
1#
0+
1-

#1752000
1!
1+
b1100110011010 1
b1100110011010 2
b11011001100110100 4
15
b1011001100110100 6
b1100110011010000000000000 7
b10000000000 8

#1753000
b1 (

#1760000
0!
0+

#1768000
1!
1%
b10000000000 &
1+
1/
b10000000000 0
b1011001100110100 1
b1011001100110100 2
b100110011001110 4
05
b100110011001110 6
b1011001100110100000000000000 7
b1110000000000 8
b110000000000 9

#1769000
b10 (
b1 )

#1776000
0!
0+

#1784000
1!
0%
1+
0/
b100110011001110 1
b100110011001110 2
b11110011001101000 4
15
b1110011001101000 6
b100110011001110000000000000 7
b110000000000 8

#1785000
b11 (

#1792000
0!
0+

#1800000
1!
1%
b110000000000 &
1+
1/
b110000000000 0
b1110011001101000 1
b1110011001101000 2
b1000000000000010 4
05
b1000000000000010 6
b1110011001101000000000000000 7
b10010000000000 8
b10000000000 9

#1801000
b100 (
b10 )

#1808000
0!
0+

#1816000
1!
0%
1+
0/
b1000000000000010 1
b1000000000000010 2
b1100110011100 4
b1100110011100 6
b1000000000000010000000000000 7
b1010000000000 8

#1817000
b101 (

#1824000
0!
0+

#1832000
1!
1+
b1100110011100 1
b1100110011100 2
b11011001100110110 4
15
b1011001100110110 6
b1100110011100000000000000 7
b10000000000 8

#1833000
b110 (

#1840000
0!
0+

#1848000
1!
1%
b10000000000 &
1+
1/
b10000000000 0
b1011001100110110 1
b1011001100110110 2
b100110011010000 4
05
b100110011010000 6
b1011001100110110000000000000 7
b1110000000000 8
b110000000000 9

#1849000
b111 (
b11 )

#1856000
0!
0+

#1864000
1!
0%
1+
0/
b100110011010000 1
b100110011010000 2
b11110011001101010 4
15
b1110011001101010 6
b100110011010000000000000000 7
b110000000000 8

#1865000
b1000 (

#1872000
0!
0+

#1880000
1!
1%
b110000000000 &
1+
1/
b110000000000 0
b1110011001101010 1
b1110011001101010 2
b1000000000000100 4
05
b1000000000000100 6
b1110011001101010000000000000 7
b10010000000000 8
b10000000000 9

#1881000
b1001 (
b100 )

#1888000
0!
0+

#1896000
1!
0%
1+
0/
b1000000000000100 1
b1000000000000100 2
b1100110011110 4
b1100110011110 6
b1000000000000100000000000000 7
b1010000000000 8

#1897000
b1010 (

#1904000
0!
0+

#1912000
1!
1+
b1100110011110 1
b1100110011110 2
b11011001100111000 4
15
b1011001100111000 6
b1100110011110000000000000 7
b10000000000 8

#1913000
b1011 (

#1920000
0!
0+

#1928000
1!
1%
b10000000000 &
1+
1/
b10000000000 0
b1011001100111000 1
b1011001100111000 2
b100110011010010 4
05
b100110011010010 6
b1011001100111000000000000000 7
b1110000000000 8
b110000000000 9

#1929000
b1100 (
b101 )

#1936000
0!
0+

#1944000
1!
0%
1+
0/
b100110011010010 1
b100110011010010 2
b11110011001101100 4
15
b1110011001101100 6
b100110011010010000000000000 7
b110000000000 8

#1945000
b1101 (

#1952000
0!
0+

#1960000
1!
1%
b110000000000 &
1+
1/
b110000000000 0
b1110011001101100 1
b1110011001101100 2
b1000000000000110 4
05
b1000000000000110 6
b1110011001101100000000000000 7
b10010000000001 8
b10000000001 9

#1961000
b1110 (
b110 )

#1968000
0!
0+

#1976000
1!
0%
1+
0/
b1000000000000110 1
b1000000000000110 2
b1100110100000 4
b1100110100000 6
b1000000000000110000000000000 7
b1010000000001 8

#1977000
b1111 (

#1984000
0!
0+

#1992000
1!
1+
b1100110100000 1
b1100110100000 2
b11011001100111010 4
15
b1011001100111010 6
b1100110100000000000000000 7
b10000000001 8

#1993000
b10000 (

#2000000
0!
0+

#2008000
1!
1%
b10000000001 &
1+
1/
b10000000001 0
b1011001100111010 1
b1011001100111010 2
b100110011010100 4
05
b100110011010100 6
b1011001100111010000000000000 7
b1110000000001 8
b110000000001 9

#2009000
b10001 (
b111 )

#2016000
0!
0+

#2024000
1!
0%
1+
0/
b100110011010100 1
b100110011010100 2
b11110011001101110 4
15
b1110011001101110 6
b100110011010100000000000000 7
b110000000001 8

#2025000
b10010 (

#2032000
0!
0+

