vkr_sync_hdl/rtl/sync_farrow_parab.v
`timescale 1ns / 1ps
//==========================================================================
// Проект       : ВКР — символьная синхронизация SDR, Глава 3
// Модуль       : sync_farrow_parab
// Описание     : Кусочно-параболический интерполятор Фарроу, коэффициент α = 1/2
//                Формирует XI = (v2*μ + v1)*μ + v0 по схеме Горнера из
//                четырёх последних входных комплексных отсчётов и дробной
//                задержки μ, поступающей от sync_mod1_nco.
//
// Базовые формулы (Rice, Digital Communications: A Discrete-Time Approach,
//                  раздел 8.4.2; идентично коду parse_deb_data.m советника):
//   v2 = ( x[n]   -   x[n-1] -   x[n-2] +   x[n-3]) / 2
//   v1 = (-x[n]   + 3*x[n-1] -   x[n-2] -   x[n-3]) / 2
//   v0 =   x[n-2]
//   XI = (v2*μ + v1)*μ + v0     (схема Горнера, 2 последовательных умножения)
//
// Конвейер     : 3 такта clk от in_valid до out_valid
//                Ступень 1: регистрируются v0, v1, v2, μ (латентность 1)
//                Ступень 2: t = v2*μ + v1                 (латентность 1)
//                Ступень 3: XI = t*μ + v0 + округление    (латентность 1)
//
// Ресурсы      : 4 × DSP48E1 (две ступени Горнера × два канала I/Q)
//                Умножение на 3 внутри v1 реализовано как shift+add, без DSP
//
// Интерфейс    : синхронный, однотактный. Сигнал in_valid может быть
//                снят и снова поднят; латентность 3 такта сохраняется.
//                μ обновляется извне NCO и используется как есть в момент
//                регистрации v-коэффициентов.
//
// Автор        : Кудимов А.А., ВКР магистра, 2026
//==========================================================================
module sync_farrow_parab #(
    parameter W_IN  = 16,   // разрядность вход/выход I, Q; знаковое Q1.(W_IN-1)
    parameter W_MU  = 12,   // разрядность μ; беззнаковое Q0.W_MU, μ ∈ [0, 1)
    parameter W_OUT = 16    // выходная разрядность интерполянта
)(
    input  wire                          clk,
    input  wire                          reset,     // asynchronous, active-high
    // входной поток
    input  wire                          in_valid,
    input  wire signed [W_IN-1:0]        in_i,
    input  wire signed [W_IN-1:0]        in_q,
    input  wire        [W_MU-1:0]        mu_in,     // μ от sync_mod1_nco
    // выход
    output wire                          out_valid,
    output wire signed [W_OUT-1:0]       xi_i,
    output wire signed [W_OUT-1:0]       xi_q
);

//--------------------------------------------------------------------------
// Расчёт разрядностей промежуточных сигналов
//--------------------------------------------------------------------------
// v-коэффициенты: максимум по модулю |v1| ≈ 3|x|_max; нужно
//   W_V = W_IN + 2 бит знакового (1 бит на сумму 4 членов, 1 на умножение на 3)
localparam W_V = W_IN + 2;

// μ интерпретируется как беззнаковое, но для умножения расширяется на 1 бит
// знакового нуля — W_MUS = W_MU + 1
localparam W_MUS = W_MU + 1;

// Произведение v × μ: разрядность W_V + W_MUS = W_IN + W_MU + 3 бит знакового
localparam W_MUL = W_V + W_MUS;

//--------------------------------------------------------------------------
// Ступень 0 (комбинационная): линия задержки на 3 регистра, x[n] берётся
// напрямую со входа. Это эквивалентно 4-элементной линии задержки, но
// экономит один W_IN-битный регистр на канал.
//--------------------------------------------------------------------------
reg signed [W_IN-1:0] dl_i1, dl_i2, dl_i3;
reg signed [W_IN-1:0] dl_q1, dl_q2, dl_q3;

always @(posedge clk or posedge reset) begin
    if (reset) begin
        dl_i1 <= 0; dl_i2 <= 0; dl_i3 <= 0;
        dl_q1 <= 0; dl_q2 <= 0; dl_q3 <= 0;
    end else if (in_valid) begin
        // Порядок обновления неважен — non-blocking assignments работают параллельно
        dl_i1 <= in_i;   dl_i2 <= dl_i1;   dl_i3 <= dl_i2;
        dl_q1 <= in_q;   dl_q2 <= dl_q1;   dl_q3 <= dl_q2;
    end
end

// Расширение разрядности отсчётов линии задержки до W_V бит (sign-extension)
wire signed [W_V-1:0] x0_i = $signed(in_i);    // x[n]
wire signed [W_V-1:0] x1_i = $signed(dl_i1);   // x[n-1]
wire signed [W_V-1:0] x2_i = $signed(dl_i2);   // x[n-2], базовый отсчёт
wire signed [W_V-1:0] x3_i = $signed(dl_i3);   // x[n-3]
wire signed [W_V-1:0] x0_q = $signed(in_q);
wire signed [W_V-1:0] x1_q = $signed(dl_q1);
wire signed [W_V-1:0] x2_q = $signed(dl_q2);
wire signed [W_V-1:0] x3_q = $signed(dl_q3);

//--------------------------------------------------------------------------
// Ступень 1: вычисление v0, v1, v2 и регистрация
// Умножение на 3 выполнено как (x << 1) + x — без DSP48.
// Деление на 2 выполнено арифметическим сдвигом >>> 1.
//--------------------------------------------------------------------------
wire signed [W_V-1:0] v2_c_i = (x0_i - x1_i - x2_i + x3_i) >>> 1;
wire signed [W_V-1:0] v1_c_i = (-x0_i + (x1_i <<< 1) + x1_i - x2_i - x3_i) >>> 1;
wire signed [W_V-1:0] v0_c_i = x2_i;

wire signed [W_V-1:0] v2_c_q = (x0_q - x1_q - x2_q + x3_q) >>> 1;
wire signed [W_V-1:0] v1_c_q = (-x0_q + (x1_q <<< 1) + x1_q - x2_q - x3_q) >>> 1;
wire signed [W_V-1:0] v0_c_q = x2_q;

reg signed [W_V-1:0]  v2_s1_i, v1_s1_i, v0_s1_i;
reg signed [W_V-1:0]  v2_s1_q, v1_s1_q, v0_s1_q;
reg        [W_MU-1:0] mu_s1;
reg                   valid_s1;

always @(posedge clk or posedge reset) begin
    if (reset) begin
        v2_s1_i <= 0; v1_s1_i <= 0; v0_s1_i <= 0;
        v2_s1_q <= 0; v1_s1_q <= 0; v0_s1_q <= 0;
        mu_s1    <= 0;
        valid_s1 <= 1'b0;
    end else begin
        if (in_valid) begin
            v2_s1_i <= v2_c_i; v1_s1_i <= v1_c_i; v0_s1_i <= v0_c_i;
            v2_s1_q <= v2_c_q; v1_s1_q <= v1_c_q; v0_s1_q <= v0_c_q;
            mu_s1   <= mu_in;
        end
        valid_s1 <= in_valid;
    end
end

//--------------------------------------------------------------------------
// Ступень 2: первая ступень Горнера
//    t = v2 · μ + v1
// μ интерпретируется как Q0.W_MU беззнаковое, расширено до W_MUS = W_MU + 1
// бит знакового с нулевым MSB — это допустимо, так как μ ∈ [0, 1).
//
// v2 · μ имеет масштаб Q(W_V - W_MU - 1).(W_MU + W_V - 1) в битах W_MUL
// v1 выравнивается сдвигом влево на W_MU бит и складывается.
//--------------------------------------------------------------------------
wire signed [W_MUS-1:0] mu_s1_sgn = {1'b0, mu_s1};

// Произведение v2 · μ (знаковое × знаковое с нулевым MSB)
wire signed [W_MUL-1:0] v2_mul_mu_i = v2_s1_i * mu_s1_sgn;
wire signed [W_MUL-1:0] v2_mul_mu_q = v2_s1_q * mu_s1_sgn;

// v1, сдвинутое влево на W_MU для выравнивания по масштабу с произведением
wire signed [W_MUL-1:0] v1_aligned_i = {{(W_MUS){v1_s1_i[W_V-1]}}, v1_s1_i} <<< W_MU;
wire signed [W_MUL-1:0] v1_aligned_q = {{(W_MUS){v1_s1_q[W_V-1]}}, v1_s1_q} <<< W_MU;

wire signed [W_MUL:0] t_full_i = $signed({v2_mul_mu_i[W_MUL-1], v2_mul_mu_i}) +
                                 $signed({v1_aligned_i[W_MUL-1], v1_aligned_i});
wire signed [W_MUL:0] t_full_q = $signed({v2_mul_mu_q[W_MUL-1], v2_mul_mu_q}) +
                                 $signed({v1_aligned_q[W_MUL-1], v1_aligned_q});

// Регистр промежуточного результата; для первой итерации храним полную точность
reg signed [W_MUL:0]   t_s2_i, t_s2_q;
reg signed [W_V-1:0]   v0_s2_i, v0_s2_q;
reg        [W_MU-1:0]  mu_s2;
reg                    valid_s2;

always @(posedge clk or posedge reset) begin
    if (reset) begin
        t_s2_i <= 0; t_s2_q <= 0;
        v0_s2_i <= 0; v0_s2_q <= 0;
        mu_s2   <= 0;
        valid_s2 <= 1'b0;
    end else begin
        if (valid_s1) begin
            t_s2_i <= t_full_i;
            t_s2_q <= t_full_q;
            v0_s2_i <= v0_s1_i;
            v0_s2_q <= v0_s1_q;
            mu_s2   <= mu_s1;
        end
        valid_s2 <= valid_s1;
    end
end

//--------------------------------------------------------------------------
// Ступень 3: вторая ступень Горнера
//    XI_scaled = t · μ + v0_aligned
// Масштаб t — Q(W_V - W_MU).(2·W_MU); после умножения на μ — Q.(W_MU)
// Для выхода XI в формате Q1.(W_OUT-1) округляем и обрезаем.
//--------------------------------------------------------------------------
wire signed [W_MUS-1:0] mu_s2_sgn = {1'b0, mu_s2};

// Произведение t · μ; t имеет W_MUL+1 бит, μ — W_MUS бит
localparam W_MUL2 = (W_MUL + 1) + W_MUS;
wire signed [W_MUL2-1:0] t_mul_mu_i = t_s2_i * mu_s2_sgn;
wire signed [W_MUL2-1:0] t_mul_mu_q = t_s2_q * mu_s2_sgn;

// v0 выравнивается сдвигом влево на 2·W_MU (он был Q(W_V-1).0, нужно .2W_MU)
wire signed [W_MUL2-1:0] v0_aligned_i = {{(W_MUS + W_MU){v0_s2_i[W_V-1]}}, v0_s2_i} <<< (2*W_MU);
wire signed [W_MUL2-1:0] v0_aligned_q = {{(W_MUS + W_MU){v0_s2_q[W_V-1]}}, v0_s2_q} <<< (2*W_MU);

// Полный результат XI в формате Q.(2·W_MU)
wire signed [W_MUL2:0] xi_scaled_i = $signed({t_mul_mu_i[W_MUL2-1], t_mul_mu_i}) +
                                     $signed({v0_aligned_i[W_MUL2-1], v0_aligned_i});
wire signed [W_MUL2:0] xi_scaled_q = $signed({t_mul_mu_q[W_MUL2-1], t_mul_mu_q}) +
                                     $signed({v0_aligned_q[W_MUL2-1], v0_aligned_q});

// Округление half-up и усечение до W_OUT бит знакового
// Q-формат анализ:
//   v   : Q3.(W_IN-1)    — W_V бит знакового (3 целых с учётом *3 и суммы 4 элементов)
//   μ   : Q0.W_MU        — беззнаковое
//   v·μ : Q3.(W_IN-1+W_MU)
//   t·μ : Q3.(W_IN-1+2·W_MU) = xi_scaled
//   Для выхода Q1.(W_OUT-1) при W_OUT = W_IN нужен сдвиг на 2·W_MU бит
//   (старшие биты сверх W_OUT — это «запас» Q3 → Q1, проверяется на overflow)
localparam SHIFT_OUT = 2*W_MU;

// Округляющая константа: 1 << (SHIFT_OUT - 1)
wire signed [W_MUL2:0] round_const = (SHIFT_OUT > 0) ? ({{(W_MUL2){1'b0}}, 1'b1} <<< (SHIFT_OUT - 1)) : 0;

wire signed [W_MUL2:0] xi_rounded_i = xi_scaled_i + round_const;
wire signed [W_MUL2:0] xi_rounded_q = xi_scaled_q + round_const;

// Насыщающее усечение до W_OUT бит
// После сдвига вправо на SHIFT_OUT бит старшие биты должны быть равны знаку,
// иначе имеет место переполнение (и нужно насыщение до ±max)
wire signed [W_MUL2-SHIFT_OUT:0] xi_shifted_i = xi_rounded_i >>> SHIFT_OUT;
wire signed [W_MUL2-SHIFT_OUT:0] xi_shifted_q = xi_rounded_q >>> SHIFT_OUT;

// Максимальные значения для насыщения Q1.(W_OUT-1)
localparam signed [W_OUT-1:0] SAT_POS = {1'b0, {(W_OUT-1){1'b1}}};  // +2^(W_OUT-1)-1
localparam signed [W_OUT-1:0] SAT_NEG = {1'b1, {(W_OUT-1){1'b0}}};  // -2^(W_OUT-1)

reg signed [W_OUT-1:0] xi_s3_i, xi_s3_q;
reg                    valid_s3;

// Проверка переполнения: старшие биты должны совпадать со знаком
wire overflow_i = ~((&xi_shifted_i[W_MUL2-SHIFT_OUT : W_OUT-1]) |
                    (~(|xi_shifted_i[W_MUL2-SHIFT_OUT : W_OUT-1])));
wire overflow_q = ~((&xi_shifted_q[W_MUL2-SHIFT_OUT : W_OUT-1]) |
                    (~(|xi_shifted_q[W_MUL2-SHIFT_OUT : W_OUT-1])));

always @(posedge clk or posedge reset) begin
    if (reset) begin
        xi_s3_i <= 0; xi_s3_q <= 0;
        valid_s3 <= 1'b0;
    end else begin
        if (valid_s2) begin
            // Насыщение при переполнении
            if (overflow_i)
                xi_s3_i <= xi_shifted_i[W_MUL2-SHIFT_OUT] ? SAT_NEG : SAT_POS;
            else
                xi_s3_i <= xi_shifted_i[W_OUT-1:0];

            if (overflow_q)
                xi_s3_q <= xi_shifted_q[W_MUL2-SHIFT_OUT] ? SAT_NEG : SAT_POS;
            else
                xi_s3_q <= xi_shifted_q[W_OUT-1:0];
        end
        valid_s3 <= valid_s2;
    end
end

assign xi_i = xi_s3_i;
assign xi_q = xi_s3_q;
assign out_valid = valid_s3;

endmodule
//==========================================================================
// end of module sync_farrow_parab
//==========================================================================

vkr_sync_hdl/sim/tb_sync_farrow_parab.v
`timescale 1ns / 1ps
//==========================================================================
// Тестбенч     : tb_sync_farrow_parab
// Описание     : Bit-accurate верификация модуля sync_farrow_parab
//                Читает входные отсчёты I/Q и значения μ из файлов stimulus,
//                прогоняет через модуль, пишет выходной интерполянт в файл.
//                Параллельно MATLAB-скрипт test_sync_farrow_parab.m
//                формирует золотой вектор тех же входов и сравнивает результат.
//
// Формат файлов:
//    stimulus_in.txt   — ASCII, по одному числу на строку, W_IN-битное целое
//                        со знаком. Порядок: i0 q0 i1 q1 i2 q2 ... (4 строки на отсчёт)
//                        Последняя величина в строке — значение μ (беззнаковое W_MU бит).
//                        Итого 3 числа на тактовый период in_valid.
//    stimulus_mu.txt   — отдельный файл μ (по одному значению на такт)
//    out_hdl.txt       — вывод ASCII: i_out q_out valid (по одной строке на такт)
//==========================================================================
module tb_sync_farrow_parab;

// Параметры моделирования
localparam W_IN  = 16;
localparam W_MU  = 12;
localparam W_OUT = 16;
localparam CLK_PERIOD = 16;     // 62.5 МГц — типично для выхода DDC AD9361
localparam MAX_SAMPLES = 20000;

// Сигналы DUT
reg                      clk;
reg                      reset;
reg                      in_valid;
reg  signed [W_IN-1:0]   in_i;
reg  signed [W_IN-1:0]   in_q;
reg         [W_MU-1:0]   mu_in;
wire                     out_valid;
wire signed [W_OUT-1:0]  xi_i;
wire signed [W_OUT-1:0]  xi_q;

// Подключение DUT
sync_farrow_parab #(
    .W_IN  (W_IN),
    .W_MU  (W_MU),
    .W_OUT (W_OUT)
) dut (
    .clk       (clk),
    .reset     (reset),
    .in_valid  (in_valid),
    .in_i      (in_i),
    .in_q      (in_q),
    .mu_in     (mu_in),
    .out_valid (out_valid),
    .xi_i      (xi_i),
    .xi_q      (xi_q)
);

// Генератор тактового сигнала
initial clk = 1'b0;
always #(CLK_PERIOD/2) clk = ~clk;

// Память входных стимулов
reg signed [W_IN-1:0]  stim_i  [0:MAX_SAMPLES-1];
reg signed [W_IN-1:0]  stim_q  [0:MAX_SAMPLES-1];
reg        [W_MU-1:0]  stim_mu [0:MAX_SAMPLES-1];

integer n_samples;
integer i;
integer fout;

initial begin
    // Инициализация
    reset    = 1'b1;
    in_valid = 1'b0;
    in_i     = 0;
    in_q     = 0;
    mu_in    = 0;

    // Загрузка стимулов из файлов (сгенерированы скриптом gen_farrow_stimulus.m)
    for (i = 0; i < MAX_SAMPLES; i = i + 1) begin
        stim_i[i]  = 0;
        stim_q[i]  = 0;
        stim_mu[i] = 0;
    end
    $readmemh("stim_i.hex",  stim_i);
    $readmemh("stim_q.hex",  stim_q);
    $readmemh("stim_mu.hex", stim_mu);

    // Подсчёт фактического числа отсчётов (до первого «нулевого» маркера)
    n_samples = MAX_SAMPLES;
    for (i = MAX_SAMPLES-1; i >= 0; i = i - 1) begin
        if ((stim_i[i] == 0) && (stim_q[i] == 0) && (stim_mu[i] == 0)) begin
            n_samples = i;
        end
    end
    $display("[tb_sync_farrow_parab] Loaded %0d stimulus samples", n_samples);

    // Открытие выходного файла
    fout = $fopen("out_hdl.txt", "w");
    if (fout == 0) begin
        $display("[tb_sync_farrow_parab] ERROR: cannot open out_hdl.txt");
        $finish;
    end

    // Сброс
    @(posedge clk); @(posedge clk); @(posedge clk);
    @(negedge clk) reset = 1'b0;
    @(posedge clk);

    // Подача стимулов — по одному отсчёту на каждый такт clk
    for (i = 0; i < n_samples; i = i + 1) begin
        @(negedge clk);
        in_valid = 1'b1;
        in_i     = stim_i[i];
        in_q     = stim_q[i];
        mu_in    = stim_mu[i];
    end
    // Сбросить in_valid и подождать окончания конвейера (3 такта)
    @(negedge clk);
    in_valid = 1'b0;
    in_i     = 0;
    in_q     = 0;
    mu_in    = 0;

    repeat (10) @(posedge clk);

    $fclose(fout);
    $display("[tb_sync_farrow_parab] Done, output written to out_hdl.txt");
    $finish;
end

// Логирование выходных отсчётов в файл
always @(posedge clk) begin
    if (~reset) begin
        $fwrite(fout, "%0d %0d %0d\n", xi_i, xi_q, out_valid);
    end
end

// Опциональный дамп VCD для отладки
initial begin
    $dumpfile("tb_sync_farrow_parab.vcd");
    $dumpvars(0, tb_sync_farrow_parab);
end

endmodule
//==========================================================================
// end of tb_sync_farrow_parab
//==========================================================================

vkr_sync_hdl/vivado_prj/sync_farrow_parab.sim/sim_1/behav/xsim/tb_sync_farrow_parab.vcd
$date
   Fri Apr 17 11:17:18 2026
$end

$version
  2023.2
  $dumpfile ("tb_sync_farrow_parab.vcd") 
$end

$timescale
  1ps
$end

$scope module tb_sync_farrow_parab $end
$var reg 1 ! clk $end
$var reg 1 " reset $end
$var reg 1 # in_valid $end
$var reg 16 $ in_i [15:0] $end
$var reg 16 % in_q [15:0] $end
$var reg 12 & mu_in [11:0] $end
$var wire 1 ' out_valid $end
$var wire 16 ( xi_i [15:0] $end
$var wire 16 ) xi_q [15:0] $end
$var integer 32 * n_samples [31:0] $end
$var integer 32 + i [31:0] $end
$var integer 32 , fout [31:0] $end
$scope module dut $end
$var wire 1 - clk $end
$var wire 1 . reset $end
$var wire 1 / in_valid $end
$var wire 16 0 in_i [15:0] $end
$var wire 16 1 in_q [15:0] $end
$var wire 12 2 mu_in [11:0] $end
$var wire 1 ' out_valid $end
$var wire 16 ( xi_i [15:0] $end
$var wire 16 ) xi_q [15:0] $end
$var reg 16 3 dl_i1 [15:0] $end
$var reg 16 4 dl_i2 [15:0] $end
$var reg 16 5 dl_i3 [15:0] $end
$var reg 16 6 dl_q1 [15:0] $end
$var reg 16 7 dl_q2 [15:0] $end
$var reg 16 8 dl_q3 [15:0] $end
$var wire 18 9 x0_i [17:0] $end
$var wire 18 : x1_i [17:0] $end
$var wire 18 ; x2_i [17:0] $end
$var wire 18 < x3_i [17:0] $end
$var wire 18 = x0_q [17:0] $end
$var wire 18 > x1_q [17:0] $end
$var wire 18 ? x2_q [17:0] $end
$var wire 18 @ x3_q [17:0] $end
$var wire 18 A v2_c_i [17:0] $end
$var wire 18 B v1_c_i [17:0] $end
$var wire 18 C v0_c_i [17:0] $end
$var wire 18 D v2_c_q [17:0] $end
$var wire 18 E v1_c_q [17:0] $end
$var wire 18 F v0_c_q [17:0] $end
$var reg 18 G v2_s1_i [17:0] $end
$var reg 18 H v1_s1_i [17:0] $end
$var reg 18 I v0_s1_i [17:0] $end
$var reg 18 J v2_s1_q [17:0] $end
$var reg 18 K v1_s1_q [17:0] $end
$var reg 18 L v0_s1_q [17:0] $end
$var reg 12 M mu_s1 [11:0] $end
$var reg 1 N valid_s1 $end
$var wire 13 O mu_s1_sgn [12:0] $end
$var wire 31 P v2_mul_mu_i [30:0] $end
$var wire 31 Q v2_mul_mu_q [30:0] $end
$var wire 31 R v1_aligned_i [30:0] $end
$var wire 31 S v1_aligned_q [30:0] $end
$var wire 32 T t_full_i [31:0] $end
$var wire 32 U t_full_q [31:0] $end
$var reg 32 V t_s2_i [31:0] $end
$var reg 32 W t_s2_q [31:0] $end
$var reg 18 X v0_s2_i [17:0] $end
$var reg 18 Y v0_s2_q [17:0] $end
$var reg 12 Z mu_s2 [11:0] $end
$var reg 1 [ valid_s2 $end
$var wire 13 \ mu_s2_sgn [12:0] $end
$var wire 45 ] t_mul_mu_i [44:0] $end
$var wire 45 ^ t_mul_mu_q [44:0] $end
$var wire 45 _ v0_aligned_i [44:0] $end
$var wire 45 ` v0_aligned_q [44:0] $end
$var wire 46 a xi_scaled_i [45:0] $end
$var wire 46 b xi_scaled_q [45:0] $end
$var wire 46 c round_const [45:0] $end
$var wire 46 d xi_rounded_i [45:0] $end
$var wire 46 e xi_rounded_q [45:0] $end
$var wire 22 f xi_shifted_i [21:0] $end
$var wire 22 g xi_shifted_q [21:0] $end
$var reg 16 h xi_s3_i [15:0] $end
$var reg 16 i xi_s3_q [15:0] $end
$var reg 1 j valid_s3 $end
$var wire 1 k overflow_i $end
$var wire 1 l overflow_q $end
$upscope $end
$upscope $end
$enddefinitions $end

#0
$dumpvars
0!
1"
0#
b0 $
b0 %
b0 &
0'
b0 (
b0 )
b11001000 *
b11111111111111111111111111111111 +
b11111111111111111011000111100000 ,
0-
1.
0/
b0 0
b0 1
b0 2
b0 3
b0 4
b0 5
b0 6
b0 7
b0 8
b0 9
b0 :
b0 ;
b0 <
b0 =
b0 >
b0 ?
b0 @
b0 A
b0 B
b0 C
b0 D
b0 E
b0 F
b0 G
b0 H
b0 I
b0 J
b0 K
b0 L
b0 M
0N
b0 O
b0 P
b0 Q
b0 R
b0 S
b0 T
b0 U
b0 V
b0 W
b0 X
b0 Y
b0 Z
0[
b0 \
b0 ]
b0 ^
b0 _
b0 `
b0 a
b0 b
b100000000000000000000000 c
b100000000000000000000000 d
b100000000000000000000000 e
b0 f
b0 g
b0 h
b0 i
0j
0k
0l
$end

#8000
1!
1-

#16000
0!
0-

#24000
1!
1-

#32000
0!
0-

#40000
1!
1-

#48000
0!
0"
0-
0.

#56000
1!
b0 +
1-

#64000
0!
1#
b101100110011010 $
b100000000000 &
b1 +
0-
1/
b101100110011010 0
b100000000000 2
b101100110011010 9
b10110011001101 A
b111101001100110011 B

#72000
1!
1-
b101100110011010 3
b101100110011010 :
b0 A
b101100110011010 B
b10110011001101 G
b111101001100110011 H
b100000000000 M
1N
b100000000000 O
b1011001100110100000000000 P
b1111101001100110011000000000000 R
b11111110100110011001100000000000 T

#80000
0!
b101100001111111 $
b111000000100 %
b10 +
0-
b101100001111111 0
b111000000100 1
b101100001111111 9
b111000000100 =
b111111111101110010 A
b101101000100111 B
b11100000010 D
b111111100011111110 E

#88000
1!
1-
b101100001111111 3
b101100110011010 4
b111000000100 6
b101100001111111 :
b101100110011010 ;
b111000000100 >
b111101001100110011 A
b10101110110010 B
b101100110011010 C
b0 D
b111000000100 E
b111111111101110010 G
b101101000100111 H
b11100000010 J
b111111100011111110 K
b1111111111110111001000000000000 P
b1110000001000000000000 Q
b101101000100111000000000000 R
b1111111100011111110000000000000 S
b101100111100000000000000000 T
b11111111110001111111000000000000 U
b11111110100110011001100000000000 V
b100000000000 Z
1[
b100000000000 \
b111111111010011001100110000000000000000000000 ]
b1111111111010011001100110000000000000000000000 a
b1111111111010011001101010000000000000000000000 d
b1111111111010011001101 f

#96000
0!
b101010100110111 $
b1101110110000 %
b11 +
0-
b101010100110111 0
b1101110110000 1
b101010100110111 9
b1101110110000 =
b111101000110001111 A
b10110101010110 B
b11011010110 D
b11100101110 E

#104000
1!
1'
b1111010011001101 (
1-
b101010100110111 3
b101100001111111 4
b101100110011010 5
b1101110110000 6
b111000000100 7
b101010100110111 :
b101100001111111 ;
b101100110011010 <
b1101110110000 >
b111000000100 ?
b10001101 A
b111111110000101010 B
b101100001111111 C
b111111100011111110 D
b1010010101110 E
b111000000100 F
b111101000110001111 G
b10110101010110 H
b101100110011010 I
b11011010110 J
b11100101110 K
b1111110100011000111100000000000 P
b1101101011000000000000 Q
b10110101010110000000000000 R
b11100101110000000000000 S
b1011000011101100000000000 T
b101010011001000000000000 U
b101100111100000000000000000 V
b11111111110001111111000000000000 W
b10110011110000000000000000000000000000 ]
b111111111111000111111100000000000000000000000 ^
b10110011110000000000000000000000000000 a
b1111111111111000111111100000000000000000000000 b
b10110011110000100000000000000000000000 d
b1111111111111001000000000000000000000000000000 e
b10110011110000 f
b1111111111111001000000 g
b1111010011001101 h
1j

#112000
0!
b100111111010110 $
b10100010101101 %
b100 +
0-
b100111111010110 0
b10100010101101 1
b100111111010110 9
b10100010101101 =
b111111110111011101 A
b111111111011011011 B
b111111111101111100 D
b111000101111 E

#120000
1!
b10110011110000 (
b1111111001000000 )
1-
b100111111010110 3
b101010100110111 4
b101100001111111 5
b10100010101101 6
b1101110110000 7
b111000000100 8
b100111111010110 :
b101010100110111 ;
b101100001111111 <
b10100010101101 >
b1101110110000 ?
b111000000100 @
b110100100 A
b111111100011111011 B
b101010100110111 C
b111111100100101010 D
b1001111010011 E
b1101110110000 F
b111111110111011101 G
b111111111011011011 H
b101100001111111 I
b111111111101111100 J
b111000101111 K
b111000000100 L
b1111111111011101110100000000000 P
b1111111111110111110000000000000 Q
b1111111111011011011000000000000 R
b111000101111000000000000 S
b11111111110111001001100000000000 T
b110111101101000000000000 U
b1011000011101100000000000 V
b101010011001000000000000 W
b101100110011010 X
b101100001110110000000000000000000000 ]
b10101001100100000000000000000000000 ^
b101100110011010000000000000000000000000 _
b110010010101000110000000000000000000000 a
b10101001100100000000000000000000000 b
b110010010101001010000000000000000000000 d
b10101001101000000000000000000000000 e
b110010010101001 f
b10101001101 g
b10110011110000 h
b1111111001000000 i

#128000
0!
b100100001111101 $
b11010010101010 %
b101 +
0-
b100100001111101 0
b11010010101010 1
b100100001111101 9
b11010010101010 =
b111111110111110111 A
b111111110010100111 B
b111111111100101000 D
b110111010100 E

#136000
1!
b110010010101001 (
b10101001101 )
1-
b100100001111101 3
b100111111010110 4
b101010100110111 5
b11010010101010 6
b10100010101101 7
b1101110110000 8
b100100001111101 :
b100111111010110 ;
b101010100110111 <
b11010010101010 >
b10100010101101 ?
b1101110110000 @
b1010110000 A
b111111010111110110 B
b100111111010110 C
b111111100110000001 D
b1001001111011 E
b10100010101101 F
b111111110111110111 G
b111111110010100111 H
b101010100110111 I
b111111111100101000 J
b110111010100 K
b1101110110000 L
b1111111111011111011100000000000 P
b1111111111110010100000000000000 Q
b1111111110010100111000000000000 R
b110111010100000000000000 S
b11111111101110100010100000000000 T
b110101101000000000000000 U
b11111111110111001001100000000000 V
b110111101101000000000000 W
b101100001111111 X
b111000000100 Y
b111111111111011100100110000000000000000000000 ]
b11011110110100000000000000000000000 ^
b101100001111111000000000000000000000000 _
b111000000100000000000000000000000000 `
b101011101100011110000000000000000000000 a
b1010011111010100000000000000000000000 b
b101011101100100010000000000000000000000 d
b1010011111011000000000000000000000000 e
b101011101100100 f
b1010011111011 g
b110010010101001 h
b10101001101 i

#144000
0!
b11111101011011 $
b11111101011011 %
b110 +
0-
b11111101011011 0
b11111101011011 1
b11111101011011 9
b11111101011011 =
b111111111000011111 A
b111111101010000111 B
b111111111011011010 D
b110100100011 E

#152000
1!
b101011101100100 (
b1010011111011 )
1-
b11111101011011 3
b100100001111101 4
b100111111010110 5
b11111101011011 6
b11010010101010 7
b10100010101101 8
b11111101011011 :
b100100001111101 ;
b100111111010110 <
b11111101011011 >
b11010010101010 ?
b10100010101101 @
b1110101100 A
b111111001100110001 B
b100100001111101 C
b111111101000000001 D
b1000010101111 E
b11010010101010 F
b111111111000011111 G
b111111101010000111 H
b100111111010110 I
b111111111011011010 J
b110100100011 K
b10100010101101 L
b1111111111100001111100000000000 P
b1111111111101101101000000000000 Q
b1111111101010000111000000000000 R
b110100100011000000000000 S
b11111111100110010110100000000000 T
b110010010000000000000000 U
b11111111101110100010100000000000 V
b110101101000000000000000 W
b101010100110111 X
b1101110110000 Y
b111111111110111010001010000000000000000000000 ]
b11010110100000000000000000000000000 ^
b101010100110111000000000000000000000000 _
b1101110110000000000000000000000000000 `
b101001100001000010000000000000000000000 a
b10001001100100000000000000000000000000 b
b101001100001000110000000000000000000000 d
b10001001100100100000000000000000000000 e
b101001100001000 f
b10001001100100 g
b101011101100100 h
b1010011111011 i

#160000
0!
b11010010101010 $
b100100001111101 %
b111 +
0-
b11010010101010 0
b100100001111101 1
b11010010101010 9
b100100001111101 =
b111111111001010100 A
b111111100010001010 B
b111111111010010010 D
b110000011110 E

#168000
1!
b101001100001000 (
b10001001100100 )
1-
b11010010101010 3
b11111101011011 4
b100100001111101 5
b100100001111101 6
b11111101011011 7
b11010010101010 8
b11010010101010 :
b11111101011011 ;
b100100001111101 <
b100100001111101 >
b11111101011011 ?
b11010010101010 @
b10010010001 A
b111111000010111110 B
b11111101011011 C
b111111101010100111 D
b111001111010 E
b11111101011011 F
b111111111001010100 G
b111111100010001010 H
b100100001111101 I
b111111111010010010 J
b110000011110 K
b11010010101010 L
b1111111111100101010000000000000 P
b1111111111101001001000000000000 Q
b1111111100010001010000000000000 R
b110000011110000000000000 S
b11111111011110110100000000000000 T
b101101100111000000000000 U
b11111111100110010110100000000000 V
b110010010000000000000000 W
b100111111010110 X
b10100010101101 Y
b111111111110011001011010000000000000000000000 ]
b11001001000000000000000000000000000 ^
b100111111010110000000000000000000000000 _
b10100010101101000000000000000000000000 `
b100110010100001010000000000000000000000 a
b10111011110101000000000000000000000000 b
b100110010100001110000000000000000000000 d
b10111011110101100000000000000000000000 e
b100110010100001 f
b10111011110101 g
b101001100001000 h
b10001001100100 i

#176000
0!
b10100010101101 $
b100111111010110 %
b1000 +
0-
b10100010101101 0
b100111111010110 1
b10100010101101 9
b100111111010110 =
b111111111010010010 A
b111111011010111100 B
b111111111001010100 D
b101011001110 E

